CHANGES.txt
CONTRIBUTORS.txt
MANIFEST.in
README.txt
setup.py
inouk/__init__.py
inouk.recipe.patch.egg-info/PKG-INFO
inouk.recipe.patch.egg-info/SOURCES.txt
inouk.recipe.patch.egg-info/dependency_links.txt
inouk.recipe.patch.egg-info/entry_points.txt
inouk.recipe.patch.egg-info/namespace_packages.txt
inouk.recipe.patch.egg-info/not-zip-safe
inouk.recipe.patch.egg-info/requires.txt
inouk.recipe.patch.egg-info/top_level.txt
inouk/recipe/__init__.py
inouk/recipe/patch/__init__.py