Metadata-Version: 1.1
Name: inouk.recipe.patch
Version: 0.1.2
Summary: A buildout recipe for patching mainly designed to work with anybox.openerp.recipe
Home-page: http://bitbucket.org/cmorisse/inouk-recipe-patch
Author: Cyril MORISSE
Author-email: cmorisse at boxes3.net
License: LGPL
Keywords: buildout patch
Platform: UNKNOWN
Classifier: Framework :: Buildout
Classifier: Intended Audience :: Developers
Classifier: Topic :: Software Development :: Build Tools
Classifier: License :: OSI Approved :: GNU Library or Lesser General Public License (LGPL)
Classifier: Programming Language :: Python
